setup.py
eheapq/__init__.py
eheapq.egg-info/PKG-INFO
eheapq.egg-info/SOURCES.txt
eheapq.egg-info/dependency_links.txt
eheapq.egg-info/top_level.txt