Metadata-Version: 1.0
Name: eheapq
Version: 0.0.0
Summary: An extension to standard Python's heapq
Home-page: UNKNOWN
Author: Fridolin Pokorny
Author-email: fridex.devel@gmail.com
License: GPLv3+
Platform: UNKNOWN
